unicontext/__init__.py
unicontext/_version.py
unicontext/client.py
unicontext/exceptions.py
unicontext/factory.py
unicontext/models.py
unicontext/provider.py
unicontext/py.typed
unicontext/providers/__init__.py
unicontext/providers/_shared/__init__.py
unicontext/providers/_shared/http.py
unicontext/providers/letta/__init__.py
unicontext/providers/letta/adapter.py
unicontext/providers/mem0/__init__.py
unicontext/providers/mem0/adapter.py
unicontext/providers/supermemory/__init__.py
unicontext/providers/supermemory/adapter.py
unicontext/providers/zep/__init__.py
unicontext/providers/zep/adapter.py
unicontext-0.1.0.dist-info/LICENSE
unicontext-0.1.0.dist-info/METADATA
unicontext-0.1.0.dist-info/WHEEL
unicontext-0.1.0.dist-info/top_level.txt
unicontext-0.1.0.dist-info/RECORD
