Metadata-Version: 2.2
Name: unicontext
Version: 0.1.0
Summary: Universal Python SDK for AI memory/context providers with HTTP-first architecture
Author-email: MetacognitionAI <hello.metacognitionlabs@gmail.com>
License: MIT
Project-URL: Homepage, https://github.com/metacoglabs/unicontext
Project-URL: Documentation, https://github.com/metacoglabs/unicontext#readme
Project-URL: Repository, https://github.com/metacoglabs/unicontext
Project-URL: Issues, https://github.com/metacoglabs/unicontext/issues
Keywords: ai,memory,context,sdk,mem0,zep,letta,supermemory
Classifier: Development Status :: 4 - Beta
Classifier: Intended Audience :: Developers
Classifier: Programming Language :: Python :: 3
Classifier: Programming Language :: Python :: 3.10
Classifier: Programming Language :: Python :: 3.11
Classifier: Programming Language :: Python :: 3.12
Classifier: Topic :: Software Development :: Libraries :: Python Modules
Classifier: Topic :: Scientific/Engineering :: Artificial Intelligence
Classifier: Typing :: Typed
Requires-Python: >=3.10
License-File: LICENSE
Requires-Dist: httpx<1.0,>=0.25
Provides-Extra: mem0
Requires-Dist: mem0ai>=0.1; extra == "mem0"
Provides-Extra: supermemory
Requires-Dist: supermemory>=0.1; extra == "supermemory"
Provides-Extra: zep
Requires-Dist: zep-cloud>=0.1; extra == "zep"
Provides-Extra: letta
Requires-Dist: letta-client>=0.1; extra == "letta"
Provides-Extra: all
Requires-Dist: mem0ai>=0.1; extra == "all"
Requires-Dist: supermemory>=0.1; extra == "all"
Requires-Dist: zep-cloud>=0.1; extra == "all"
Requires-Dist: letta-client>=0.1; extra == "all"
Provides-Extra: dev
Requires-Dist: pytest<9,>=7; extra == "dev"
Requires-Dist: pytest-asyncio<1.0,>=0.23; extra == "dev"
Requires-Dist: ruff<1.0,>=0.4; extra == "dev"
Requires-Dist: mypy<2.0,>=1.0; extra == "dev"
Requires-Dist: build>=1.0; extra == "dev"
Requires-Dist: twine>=5.0; extra == "dev"
